tashan_scispark/__init__.py
tashan_scispark/__main__.py
tashan_scispark/celery_worker.py
tashan_scispark/cli.py
tashan_scispark/mcp_server.py
tashan_scispark/research_engine.py
tashan_scispark/suppress_warnings.py
tashan_scispark/app/__init__.py
tashan_scispark/app/main.py
tashan_scispark/app/api/__init__.py
tashan_scispark/app/api/common.py
tashan_scispark/app/api/urls.py
tashan_scispark/app/core/__init__.py
tashan_scispark/app/core/celery.py
tashan_scispark/app/core/config.py
tashan_scispark/app/core/moa.py
tashan_scispark/app/core/prompt.py
tashan_scispark/app/core/tpl.py
tashan_scispark/app/task/__init__.py
tashan_scispark/app/task/paper_assistant.py
tashan_scispark/app/templates/prompt/MoA_based_optimization_prompt.tpl
tashan_scispark/app/templates/prompt/extract_entity_prompt.tpl
tashan_scispark/app/templates/prompt/extract_tec_entities_prompt.tpl
tashan_scispark/app/templates/prompt/fact_extraction_prompt.tpl
tashan_scispark/app/templates/prompt/get_related_keyword_prompt.tpl
tashan_scispark/app/templates/prompt/human_ai_collaboration_prompt.tpl
tashan_scispark/app/templates/prompt/hypothesis_generate_prompt.tpl
tashan_scispark/app/templates/prompt/initial_idea_prompt.tpl
tashan_scispark/app/templates/prompt/paper_compression_prompt.tpl
tashan_scispark/app/templates/prompt/review_mechanism_prompt.tpl
tashan_scispark/app/templates/prompt/technical_optimizatio_prompt.tpl
tashan_scispark/app/templates/prompt/moa/default_aggregator_prompt.tpl
tashan_scispark/app/templates/prompt/moa/moa_idea_iteration_aggregation.tpl
tashan_scispark/app/templates/prompt/moa/moa_test.tpl
tashan_scispark/app/templates/prompt/moa/reviewer_prompt.tpl
tashan_scispark/app/utils/__init__.py
tashan_scispark/app/utils/arxiv_api.py
tashan_scispark/app/utils/llm_api.py
tashan_scispark/app/utils/memory_monitor.py
tashan_scispark/app/utils/pdf_to_md.py
tashan_scispark/app/utils/scholar_download.py
tashan_scispark/app/utils/tool.py
tashan_scispark/app/utils/wiki_search.py
tashan_scispark-1.0.8.dist-info/METADATA
tashan_scispark-1.0.8.dist-info/WHEEL
tashan_scispark-1.0.8.dist-info/entry_points.txt
tashan_scispark-1.0.8.dist-info/top_level.txt
tashan_scispark-1.0.8.dist-info/RECORD
