Metadata-Version: 2.4
Name: tashan-scispark
Version: 1.0.8
Summary: TaShan SciSpark - Academic Research Assistant MCP Server
Author: TaShan SciSpark Team
Maintainer: TaShan SciSpark Team
License: MIT
Project-URL: Homepage, https://github.com/tashan-scispark/tashan-scispark
Project-URL: Repository, https://github.com/tashan-scispark/tashan-scispark
Project-URL: Documentation, https://github.com/tashan-scispark/tashan-scispark#readme
Project-URL: Bug Tracker, https://github.com/tashan-scispark/tashan-scispark/issues
Keywords: mcp,academic,research,papers,ai,assistant,arxiv,claude
Classifier: Development Status :: 4 - Beta
Classifier: Intended Audience :: Developers
Classifier: Intended Audience :: Science/Research
Classifier: License :: OSI Approved :: MIT License
Classifier: Operating System :: OS Independent
Classifier: Programming Language :: Python :: 3
Classifier: Programming Language :: Python :: 3.8
Classifier: Programming Language :: Python :: 3.9
Classifier: Programming Language :: Python :: 3.10
Classifier: Programming Language :: Python :: 3.11
Classifier: Programming Language :: Python :: 3.12
Classifier: Topic :: Scientific/Engineering
Classifier: Topic :: Software Development :: Libraries :: Python Modules
Requires-Python: >=3.10
Requires-Dist: fastapi>=0.104.1
Requires-Dist: uvicorn>=0.24.0
Requires-Dist: starlette>=0.27.0
Requires-Dist: celery>=5.3.4
Requires-Dist: redis>=5.0.1
Requires-Dist: pandas>=2.1.3
Requires-Dist: numpy>=1.25.2
Requires-Dist: openpyxl>=3.1.2
Requires-Dist: requests>=2.31.0
Requires-Dist: httpx>=0.25.2
Requires-Dist: openai>=1.3.7
Requires-Dist: dashscope==1.14.1
Requires-Dist: tiktoken>=0.5.2
Requires-Dist: agentscope==0.1.0
Requires-Dist: arxiv>=2.1.0
Requires-Dist: beautifulsoup4>=4.12.2
Requires-Dist: py2neo>=2021.2.4
Requires-Dist: pydantic>=2.5.0
Requires-Dist: pydantic-settings>=2.1.0
Requires-Dist: jinja2>=3.1.2
Requires-Dist: psutil>=5.9.6
Requires-Dist: loguru==0.6.0
Requires-Dist: fastmcp>=2.0.0
Requires-Dist: mcp>=1.0.0
Requires-Dist: python-multipart>=0.0.6
Requires-Dist: python-dotenv>=1.0.0
Provides-Extra: dev
Requires-Dist: pytest>=7.0.0; extra == "dev"
Requires-Dist: pytest-asyncio>=0.21.0; extra == "dev"
Requires-Dist: black>=23.0.0; extra == "dev"
Requires-Dist: isort>=5.12.0; extra == "dev"
Requires-Dist: flake8>=6.0.0; extra == "dev"
Requires-Dist: mypy>=1.0.0; extra == "dev"
